[{"id":1182875,"title":"2026 年了，都有什么规划","replyCount":23,"avatar":"https://cdn.v2ex.com/avatar/f832/69c6/287613_large.png?m=1765161478","username":"510908220","lastReplyUsername":"1daydayde","lastReplyDateAgo":"几秒前","lastReplyDate":"2026-01-04 09:45:24","nodeTitle":"问与答","nodeUrl":"qna","isTop":false},{"id":1182868,"title":"2026 第一天上班，牛马们 早啊","replyCount":19,"avatar":"https://cdn.v2ex.com/avatar/a0cf/3d15/588519_large.png?m=1681289897","username":"Patrick1","lastReplyUsername":"yll","lastReplyDateAgo":"2 分钟前","lastReplyDate":"2026-01-04 09:43:18","nodeTitle":"生活","nodeUrl":"life","isTop":false},{"id":1182874,"title":"我用 Rust + GPUI 写了一个 Redis 客户端——Zedis","replyCount":7,"avatar":"https://cdn.v2ex.com/avatar/ece2/870f/646818_large.png?m=1720851173","username":"treexie","lastReplyUsername":"treexie","lastReplyDateAgo":"4 分钟前","lastReplyDate":"2026-01-04 09:41:42","nodeTitle":"分享创造","nodeUrl":"create","isTop":false},{"id":1182863,"title":"til.re - 我做了一个极简的在线倒计时工具， URL 即状态，无需注册","replyCount":5,"avatar":"https://cdn.v2ex.com/avatar/f952/a539/723217_large.png?m=1767484021","username":"me477","lastReplyUsername":"hoor","lastReplyDateAgo":"6 分钟前","lastReplyDate":"2026-01-04 09:40:08","nodeTitle":"分享创造","nodeUrl":"create","isTop":false},{"id":1182881,"title":"脚走废了，有鞋子推荐吗","replyCount":4,"avatar":"https://cdn.v2ex.com/gravatar/99138134009dda72f0872e918fa889ac?s=48&d=retro","username":"fc077","lastReplyUsername":"bincheng1979","lastReplyDateAgo":"几秒前","lastReplyDate":"2026-01-04 09:45:36","nodeTitle":"生活","nodeUrl":"life","isTop":false},{"id":1182879,"title":"老美这么猛，昨晚直接把委内瑞拉总统和他妻子逮捕到了美国","replyCount":3,"avatar":"https://cdn.v2ex.com/gravatar/0c95ab24763086ed4e53587c209fa5dd?s=48&d=retro","username":"v00O","lastReplyUsername":"nuansediao","lastReplyDateAgo":"2 分钟前","lastReplyDate":"2026-01-04 09:44:01","nodeTitle":"美国","nodeUrl":"us","isTop":false},{"id":1182869,"title":"为各种 Linux 发行版生成软件一键安装命令的项目和网站叫什么来着","replyCount":2,"avatar":"https://cdn.v2ex.com/avatar/ac5b/5683/656098_large.png?m=1767143442","username":"ykong1337","lastReplyUsername":"ykong1337","lastReplyDateAgo":"34 分钟前","lastReplyDate":"2026-01-04 09:11:46","nodeTitle":"问与答","nodeUrl":"qna","isTop":false},{"id":1182878,"title":"有没有一种设备，可以切换电脑的有线音频输出到不同的设备","replyCount":2,"avatar":"https://cdn.v2ex.com/gravatar/1b913ebf6075ecf33aaf67eff382ae7c?s=48&d=retro","username":"wxiao333","lastReplyUsername":"ivan_wl","lastReplyDateAgo":"1 分钟前","lastReplyDate":"2026-01-04 09:45:05","nodeTitle":"问与答","nodeUrl":"qna","isTop":false},{"id":1182880,"title":"硬盘的价格怎么涨这么多？什么时候能降下来？","replyCount":2,"avatar":"https://cdn.v2ex.com/avatar/6a47/f86a/368903_large.png?m=1766983327","username":"fuxintong","lastReplyUsername":"hoor","lastReplyDateAgo":"5 分钟前","lastReplyDate":"2026-01-04 09:41:05","nodeTitle":"MacBook Pro","nodeUrl":"mbp","isTop":false},{"id":1182866,"title":"需要一个 iosApp 的测试兼职","replyCount":1,"avatar":"https://cdn.v2ex.com/gravatar/0366b29d4c3fe1af2757f6672081697e?s=48&d=retro","username":"ycpcq","lastReplyUsername":"kuawo","lastReplyDateAgo":"35 分钟前","lastReplyDate":"2026-01-04 09:11:01","nodeTitle":"远程工作","nodeUrl":"remote","isTop":false},{"id":1182877,"title":"就割个痔疮当跨年吧","replyCount":1,"avatar":"https://cdn.v2ex.com/avatar/ebd5/c71c/720133_large.png?m=1758871319","username":"Zealand","lastReplyUsername":"Zealand","lastReplyDateAgo":"2 分钟前","lastReplyDate":"2026-01-04 09:43:27","nodeTitle":"健康","nodeUrl":"fit","isTop":false},{"id":1182865,"title":"Shadowrocket 可以关闭 fakeip 吗？","replyCount":0,"avatar":"https://cdn.v2ex.com/gravatar/f4d4d29b9132c5e6c2012e78d4778290?s=48&d=retro","username":"introom","lastReplyDateAgo":"1 小时 22 分钟前","lastReplyDate":"2026-01-04 08:24:02","nodeTitle":"问与答","nodeUrl":"qna","isTop":false},{"id":1182872,"title":"2025 年底碎碎念","replyCount":0,"avatar":"https://cdn.v2ex.com/gravatar/07d5ecbbe5966ea0a072afa7bf8eabf6?s=48&d=retro","username":"woodongwong","lastReplyDateAgo":"38 分钟前","lastReplyDate":"2026-01-04 09:07:46","nodeTitle":"生活","nodeUrl":"life","isTop":false}]